<INDIVIDUAL>
<ID>subject1193</ID>
<WRITING>
	<TITLE>   </TITLE>
	<DATE> 2016-12-04 16:25:44 </DATE>
	<INFO> reddit post </INFO>
	<TEXT> now i'm gonna go watch and episode </TEXT>
</WRITING>
<WRITING>
	<TITLE>   </TITLE>
	<DATE> 2016-12-02 23:28:01 </DATE>
	<INFO> reddit post </INFO>
	<TEXT> crazy that you all went to the same exact highschool  </TEXT>
</WRITING>
<WRITING>
	<TITLE>   </TITLE>
	<DATE> 2016-11-27 19:11:49 </DATE>
	<INFO> reddit post </INFO>
	<TEXT> fuck yes mini ents, 2005 stick shift </TEXT>
</WRITING>
</INDIVIDUAL>
